FuzzysecurityWindowsExploitKaifaXilieJiaocheng119/README.md
FuzzysecurityWindowsExploitKaifaXilieJiaocheng119/__init__.py
FuzzysecurityWindowsExploitKaifaXilieJiaocheng119/__main__.py
FuzzysecurityWindowsExploitKaifaXilieJiaocheng119/file.epub
FuzzysecurityWindowsExploitKaifaXilieJiaocheng119/index.html
FuzzysecurityWindowsExploitKaifaXilieJiaocheng119/css/__init__.py
FuzzysecurityWindowsExploitKaifaXilieJiaocheng119/css/annotations.css
FuzzysecurityWindowsExploitKaifaXilieJiaocheng119/css/main.css
FuzzysecurityWindowsExploitKaifaXilieJiaocheng119/css/normalize.css
FuzzysecurityWindowsExploitKaifaXilieJiaocheng119/css/popup.css
FuzzysecurityWindowsExploitKaifaXilieJiaocheng119/font/__init__.py
FuzzysecurityWindowsExploitKaifaXilieJiaocheng119/font/fontello.eot
FuzzysecurityWindowsExploitKaifaXilieJiaocheng119/font/fontello.svg
FuzzysecurityWindowsExploitKaifaXilieJiaocheng119/font/fontello.ttf
FuzzysecurityWindowsExploitKaifaXilieJiaocheng119/font/fontello.woff
FuzzysecurityWindowsExploitKaifaXilieJiaocheng119/img/__init__.py
FuzzysecurityWindowsExploitKaifaXilieJiaocheng119/img/annotator-glyph-sprite.png
FuzzysecurityWindowsExploitKaifaXilieJiaocheng119/img/annotator-icon-sprite.png
FuzzysecurityWindowsExploitKaifaXilieJiaocheng119/img/apple-touch-icon.png
FuzzysecurityWindowsExploitKaifaXilieJiaocheng119/img/cancelfullscreen.png
FuzzysecurityWindowsExploitKaifaXilieJiaocheng119/img/close.png
FuzzysecurityWindowsExploitKaifaXilieJiaocheng119/img/fullscreen.png
FuzzysecurityWindowsExploitKaifaXilieJiaocheng119/img/loader.gif
FuzzysecurityWindowsExploitKaifaXilieJiaocheng119/img/menu-icon.png
FuzzysecurityWindowsExploitKaifaXilieJiaocheng119/img/save.png
FuzzysecurityWindowsExploitKaifaXilieJiaocheng119/img/saved.png
FuzzysecurityWindowsExploitKaifaXilieJiaocheng119/img/settings-s.png
FuzzysecurityWindowsExploitKaifaXilieJiaocheng119/img/settings.png
FuzzysecurityWindowsExploitKaifaXilieJiaocheng119/img/star.png
fuzzysecurity_windows_exploit_kaifa_xilie_jiaocheng_1_19-2024.3.3.0.dist-info/METADATA
fuzzysecurity_windows_exploit_kaifa_xilie_jiaocheng_1_19-2024.3.3.0.dist-info/WHEEL
fuzzysecurity_windows_exploit_kaifa_xilie_jiaocheng_1_19-2024.3.3.0.dist-info/entry_points.txt
fuzzysecurity_windows_exploit_kaifa_xilie_jiaocheng_1_19-2024.3.3.0.dist-info/top_level.txt
fuzzysecurity_windows_exploit_kaifa_xilie_jiaocheng_1_19-2024.3.3.0.dist-info/RECORD
